Workbook

Sheet Assumptions
A1: Crumb & Co (home bakery, Chennai): Revenue Model Assumptions
A2: Legend: blue text = input you can edit. Yellow fill = my own addition or choice, not in your Financial Outline doc; verify it. Black = formula. Green = link to another tab.
A4: Item | B4: Value | C4: Source / status
A5: Weeks per month | B5: 4.33 | C5: Financial Outline, section 5
A6: Wastage and discounts (% of revenue) | B6: 0.08 | C6: Financial Outline: 8% assumption, needs verification
A7: Delivery cost per order (₹) | B7: 0 | C7: Outline leaves it out (customer pays). Enter a value to test the effect
A8: Payment / platform fee (% of revenue) | B8: 0 | C8: Outline assumes UPI is free. Enter a value to test the effect
A9: Count ongoing marketing in monthly costs? (1 = yes, 0 = no) | B9: 1 | C9: Outline's 6-month table leaves it out (1,500/month); its break-even table includes it. 1 is the cautious choice
A11: Monthly fixed costs (steady state)
A12: Item | B12: Amount (₹/month) | C12: Source / status
A13: Extra electricity and gas | B13: 2500 | C13: Financial Outline, section 2 (assumption, needs verification)
A14: Ongoing marketing (ads, referral rewards, content) | B14: 1500 | C14: Financial Outline, section 2 (assumption, needs verification)
A15: Phone, internet and apps | B15: 500 | C15: Financial Outline, section 2 (assumption, needs verification)
A16: Equipment upkeep and replacement fund | B16: 500 | C16: Financial Outline, section 2 (assumption, needs verification)
A17: Cleaning and hygiene supplies | B17: 500 | C17: Financial Outline, section 2 (assumption, needs verification)
A18: FSSAI fee, insurance and miscellaneous | B18: 300 | C18: Financial Outline, section 2 (assumption, needs verification)
A19: Total monthly fixed costs (before owner's pay) | B19: =B13+B14*B9+SUM(B15:B18) -> 5800 | C19: Formula. Equals ₹5,800 when marketing is counted, ₹4,300 when not
A20: Owner's pay (₹/month) | B20: 15000 | C20: Outline scenario of ₹15,000. Try 0 or 25,000
A22: Order ramp (orders per week)
A23: Month | B23: Orders per week | C23: Source / status
A24: 1 | B24: 9 | C24: Financial Outline ramp-up (midpoints of Marketing targets)
A25: 2 | B25: 14 | C25: Financial Outline ramp-up (midpoints of Marketing targets)
A26: 3 | B26: 18 | C26: Financial Outline ramp-up (midpoints of Marketing targets)
A27: 4 | B27: 20 | C27: Financial Outline ramp-up (midpoints of Marketing targets)
A28: 5 | B28: 23 | C28: Financial Outline ramp-up (midpoints of Marketing targets)
A29: 6 | B29: 28 | C29: Financial Outline ramp-up (midpoints of Marketing targets)
A30: 7 | B30: 30 | C30: My extension: holds at the plan's 30-a-week steady state
A31: 8 | B31: 30 | C31: My extension: holds at the plan's 30-a-week steady state
A32: 9 | B32: 30 | C32: My extension: holds at the plan's 30-a-week steady state
A33: 10 | B33: 30 | C33: My extension: holds at the plan's 30-a-week steady state
A34: 11 | B34: 30 | C34: My extension: holds at the plan's 30-a-week steady state
A35: 12 | B35: 30 | C35: My extension: holds at the plan's 30-a-week steady state

Sheet Products
A1: Products and Unit Economics (₹)
A2: Prices, costs and order mix are from your Financial Outline (assumptions, unverified). Blue = input.
A4: Product | B4: Selling price | C4: Ingredients | D4: Packaging | E4: Total variable cost | F4: Cost as % of price | G4: Contribution per unit | H4: Contribution % | I4: Orders per week (steady state) | J4: Share of orders | K4: Weekly revenue | L4: Weekly contribution (before wastage)
A5: Eggless cake, ½ kg | B5: 750 | C5: 230 | D5: 60 | E5: =C5+D5 -> 290 | F5: =IF(B5=0,0,E5/B5) -> 0.38666667 | G5: =B5-E5 -> 460 | H5: =IF(B5=0,0,G5/B5) -> 0.61333333 | I5: 8 | J5: =IF($I$10=0,0,I5/$I$10) -> 0.26666667 | K5: =B5*I5 -> 6000 | L5: =G5*I5 -> 3680
A6: Eggless cake, 1 kg | B6: 1400 | C6: 430 | D6: 90 | E6: =C6+D6 -> 520 | F6: =IF(B6=0,0,E6/B6) -> 0.37142857 | G6: =B6-E6 -> 880 | H6: =IF(B6=0,0,G6/B6) -> 0.62857143 | I6: 3 | J6: =IF($I$10=0,0,I6/$I$10) -> 0.1 | K6: =B6*I6 -> 4200 | L6: =G6*I6 -> 2640
A7: Brownie box (6) | B7: 480 | C7: 150 | D7: 35 | E7: =C7+D7 -> 185 | F7: =IF(B7=0,0,E7/B7) -> 0.38541667 | G7: =B7-E7 -> 295 | H7: =IF(B7=0,0,G7/B7) -> 0.61458333 | I7: 9 | J7: =IF($I$10=0,0,I7/$I$10) -> 0.3 | K7: =B7*I7 -> 4320 | L7: =G7*I7 -> 2655
A8: Cookie box (10) | B8: 400 | C8: 120 | D8: 30 | E8: =C8+D8 -> 150 | F8: =IF(B8=0,0,E8/B8) -> 0.375 | G8: =B8-E8 -> 250 | H8: =IF(B8=0,0,G8/B8) -> 0.625 | I8: 7 | J8: =IF($I$10=0,0,I8/$I$10) -> 0.23333333 | K8: =B8*I8 -> 2800 | L8: =G8*I8 -> 1750
A9: Gift hamper | B9: 900 | C9: 270 | D9: 80 | E9: =C9+D9 -> 350 | F9: =IF(B9=0,0,E9/B9) -> 0.38888889 | G9: =B9-E9 -> 550 | H9: =IF(B9=0,0,G9/B9) -> 0.61111111 | I9: 3 | J9: =IF($I$10=0,0,I9/$I$10) -> 0.1 | K9: =B9*I9 -> 2700 | L9: =G9*I9 -> 1650
A10: Total | I10: =SUM(I5:I9) -> 30 | J10: =SUM(J5:J9) -> 1 | K10: =SUM(K5:K9) -> 20020 | L10: =SUM(L5:L9) -> 12375
A12: Per-order summary (weighted by order mix)
A13: Measure | B13: Value (₹)
A14: Average order value | B14: =SUMPRODUCT(B5:B9,J5:J9) -> 667.33333
A15: Ingredients and packaging per order | B15: =SUMPRODUCT(E5:E9,J5:J9) -> 254.83333
A16: Wastage and discounts per order | B16: =B14*Assumptions!B6 -> 53.386667
A17: Delivery cost per order | B17: =Assumptions!B7 -> 0
A18: Payment / platform fees per order | B18: =B14*Assumptions!B8 -> 0
A19: Total variable cost per order | B19: =SUM(B15:B18) -> 308.22
A20: Contribution per order | B20: =B14-B19 -> 359.11333
A22: Check: your outline shows ₹667 average order value, ₹255 ingredients and packaging, ₹53 wastage and ₹359 contribution per order.

Sheet Monthly Projection
A1: 12-Month Projection (₹)
A2: All cells are formulas driven by Assumptions and Products. Months 1 to 6 follow the Financial Outline ramp.
A4: Month | B4: Orders per week | C4: Orders in month | D4: Revenue | E4: Ingredients and packaging | F4: Wastage, delivery and fees | G4: Fixed costs | H4: Owner's pay | I4: Total costs | J4: Surplus before owner's pay | K4: Surplus after owner's pay | L4: Cumulative surplus (after pay) | M4: Cash position vs startup cost | N4: Paid back? (1 = yes)
A5: 1 | B5: =Assumptions!B24 -> 9 | C5: =B5*Assumptions!$B$5 -> 38.97 | D5: =C5*Products!$B$14 -> 26005.98 | E5: =C5*Products!$B$15 -> 9930.855 | F5: =C5*(Products!$B$16+Products!$B$17+Products!$B$18) -> 2080.4784 | G5: =Assumptions!$B$19 -> 5800 | H5: =Assumptions!$B$20 -> 15000 | I5: =E5+F5+G5+H5 -> 32811.333 | J5: =D5-E5-F5-G5 -> 8194.6466 | K5: =J5-H5 -> -6805.3534 | L5: =K5 -> -6805.3534 | M5: =L5-'Break-even and Startup'!$B$10 -> -106805.35 | N5: =IF(M5>=0,1,0) -> 0
A6: 2 | B6: =Assumptions!B25 -> 14 | C6: =B6*Assumptions!$B$5 -> 60.62 | D6: =C6*Products!$B$14 -> 40453.747 | E6: =C6*Products!$B$15 -> 15447.997 | F6: =C6*(Products!$B$16+Products!$B$17+Products!$B$18) -> 3236.2997 | G6: =Assumptions!$B$19 -> 5800 | H6: =Assumptions!$B$20 -> 15000 | I6: =E6+F6+G6+H6 -> 39484.296 | J6: =D6-E6-F6-G6 -> 15969.45 | K6: =J6-H6 -> 969.45027 | L6: =L5+K6 -> -5835.9031 | M6: =L6-'Break-even and Startup'!$B$10 -> -105835.9 | N6: =IF(M6>=0,1,0) -> 0
A7: 3 | B7: =Assumptions!B26 -> 18 | C7: =B7*Assumptions!$B$5 -> 77.94 | D7: =C7*Products!$B$14 -> 52011.96 | E7: =C7*Products!$B$15 -> 19861.71 | F7: =C7*(Products!$B$16+Products!$B$17+Products!$B$18) -> 4160.9568 | G7: =Assumptions!$B$19 -> 5800 | H7: =Assumptions!$B$20 -> 15000 | I7: =E7+F7+G7+H7 -> 44822.667 | J7: =D7-E7-F7-G7 -> 22189.293 | K7: =J7-H7 -> 7189.2932 | L7: =L6+K7 -> 1353.3901 | M7: =L7-'Break-even and Startup'!$B$10 -> -98646.61 | N7: =IF(M7>=0,1,0) -> 0
A8: 4 | B8: =Assumptions!B27 -> 20 | C8: =B8*Assumptions!$B$5 -> 86.6 | D8: =C8*Products!$B$14 -> 57791.067 | E8: =C8*Products!$B$15 -> 22068.567 | F8: =C8*(Products!$B$16+Products!$B$17+Products!$B$18) -> 4623.2853 | G8: =Assumptions!$B$19 -> 5800 | H8: =Assumptions!$B$20 -> 15000 | I8: =E8+F8+G8+H8 -> 47491.852 | J8: =D8-E8-F8-G8 -> 25299.215 | K8: =J8-H8 -> 10299.215 | L8: =L7+K8 -> 11652.605 | M8: =L8-'Break-even and Startup'!$B$10 -> -88347.395 | N8: =IF(M8>=0,1,0) -> 0
A9: 5 | B9: =Assumptions!B28 -> 23 | C9: =B9*Assumptions!$B$5 -> 99.59 | D9: =C9*Products!$B$14 -> 66459.727 | E9: =C9*Products!$B$15 -> 25378.852 | F9: =C9*(Products!$B$16+Products!$B$17+Products!$B$18) -> 5316.7781 | G9: =Assumptions!$B$19 -> 5800 | H9: =Assumptions!$B$20 -> 15000 | I9: =E9+F9+G9+H9 -> 51495.63 | J9: =D9-E9-F9-G9 -> 29964.097 | K9: =J9-H9 -> 14964.097 | L9: =L8+K9 -> 26616.702 | M9: =L9-'Break-even and Startup'!$B$10 -> -73383.298 | N9: =IF(M9>=0,1,0) -> 0
A10: 6 | B10: =Assumptions!B29 -> 28 | C10: =B10*Assumptions!$B$5 -> 121.24 | D10: =C10*Products!$B$14 -> 80907.493 | E10: =C10*Products!$B$15 -> 30895.993 | F10: =C10*(Products!$B$16+Products!$B$17+Products!$B$18) -> 6472.5995 | G10: =Assumptions!$B$19 -> 5800 | H10: =Assumptions!$B$20 -> 15000 | I10: =E10+F10+G10+H10 -> 58168.593 | J10: =D10-E10-F10-G10 -> 37738.901 | K10: =J10-H10 -> 22738.901 | L10: =L9+K10 -> 49355.602 | M10: =L10-'Break-even and Startup'!$B$10 -> -50644.398 | N10: =IF(M10>=0,1,0) -> 0
A11: 7 | B11: =Assumptions!B30 -> 30 | C11: =B11*Assumptions!$B$5 -> 129.9 | D11: =C11*Products!$B$14 -> 86686.6 | E11: =C11*Products!$B$15 -> 33102.85 | F11: =C11*(Products!$B$16+Products!$B$17+Products!$B$18) -> 6934.928 | G11: =Assumptions!$B$19 -> 5800 | H11: =Assumptions!$B$20 -> 15000 | I11: =E11+F11+G11+H11 -> 60837.778 | J11: =D11-E11-F11-G11 -> 40848.822 | K11: =J11-H11 -> 25848.822 | L11: =L10+K11 -> 75204.424 | M11: =L11-'Break-even and Startup'!$B$10 -> -24795.576 | N11: =IF(M11>=0,1,0) -> 0
A12: 8 | B12: =Assumptions!B31 -> 30 | C12: =B12*Assumptions!$B$5 -> 129.9 | D12: =C12*Products!$B$14 -> 86686.6 | E12: =C12*Products!$B$15 -> 33102.85 | F12: =C12*(Products!$B$16+Products!$B$17+Products!$B$18) -> 6934.928 | G12: =Assumptions!$B$19 -> 5800 | H12: =Assumptions!$B$20 -> 15000 | I12: =E12+F12+G12+H12 -> 60837.778 | J12: =D12-E12-F12-G12 -> 40848.822 | K12: =J12-H12 -> 25848.822 | L12: =L11+K12 -> 101053.25 | M12: =L12-'Break-even and Startup'!$B$10 -> 1053.2461 | N12: =IF(M12>=0,1,0) -> 1
A13: 9 | B13: =Assumptions!B32 -> 30 | C13: =B13*Assumptions!$B$5 -> 129.9 | D13: =C13*Products!$B$14 -> 86686.6 | E13: =C13*Products!$B$15 -> 33102.85 | F13: =C13*(Products!$B$16+Products!$B$17+Products!$B$18) -> 6934.928 | G13: =Assumptions!$B$19 -> 5800 | H13: =Assumptions!$B$20 -> 15000 | I13: =E13+F13+G13+H13 -> 60837.778 | J13: =D13-E13-F13-G13 -> 40848.822 | K13: =J13-H13 -> 25848.822 | L13: =L12+K13 -> 126902.07 | M13: =L13-'Break-even and Startup'!$B$10 -> 26902.068 | N13: =IF(M13>=0,1,0) -> 1
A14: 10 | B14: =Assumptions!B33 -> 30 | C14: =B14*Assumptions!$B$5 -> 129.9 | D14: =C14*Products!$B$14 -> 86686.6 | E14: =C14*Products!$B$15 -> 33102.85 | F14: =C14*(Products!$B$16+Products!$B$17+Products!$B$18) -> 6934.928 | G14: =Assumptions!$B$19 -> 5800 | H14: =Assumptions!$B$20 -> 15000 | I14: =E14+F14+G14+H14 -> 60837.778 | J14: =D14-E14-F14-G14 -> 40848.822 | K14: =J14-H14 -> 25848.822 | L14: =L13+K14 -> 152750.89 | M14: =L14-'Break-even and Startup'!$B$10 -> 52750.89 | N14: =IF(M14>=0,1,0) -> 1
A15: 11 | B15: =Assumptions!B34 -> 30 | C15: =B15*Assumptions!$B$5 -> 129.9 | D15: =C15*Products!$B$14 -> 86686.6 | E15: =C15*Products!$B$15 -> 33102.85 | F15: =C15*(Products!$B$16+Products!$B$17+Products!$B$18) -> 6934.928 | G15: =Assumptions!$B$19 -> 5800 | H15: =Assumptions!$B$20 -> 15000 | I15: =E15+F15+G15+H15 -> 60837.778 | J15: =D15-E15-F15-G15 -> 40848.822 | K15: =J15-H15 -> 25848.822 | L15: =L14+K15 -> 178599.71 | M15: =L15-'Break-even and Startup'!$B$10 -> 78599.712 | N15: =IF(M15>=0,1,0) -> 1
A16: 12 | B16: =Assumptions!B35 -> 30 | C16: =B16*Assumptions!$B$5 -> 129.9 | D16: =C16*Products!$B$14 -> 86686.6 | E16: =C16*Products!$B$15 -> 33102.85 | F16: =C16*(Products!$B$16+Products!$B$17+Products!$B$18) -> 6934.928 | G16: =Assumptions!$B$19 -> 5800 | H16: =Assumptions!$B$20 -> 15000 | I16: =E16+F16+G16+H16 -> 60837.778 | J16: =D16-E16-F16-G16 -> 40848.822 | K16: =J16-H16 -> 25848.822 | L16: =L15+K16 -> 204448.53 | M16: =L16-'Break-even and Startup'!$B$10 -> 104448.53 | N16: =IF(M16>=0,1,0) -> 1
A17: Total | C17: =SUM(C5:C16) -> 1264.36 | D17: =SUM(D5:D16) -> 843749.57 | E17: =SUM(E5:E16) -> 322201.07 | F17: =SUM(F5:F16) -> 67499.966 | G17: =SUM(G5:G16) -> 69600 | H17: =SUM(H5:H16) -> 180000 | I17: =SUM(I5:I16) -> 639301.04 | J17: =SUM(J5:J16) -> 384448.53 | K17: =SUM(K5:K16) -> 204448.53
A19: Tie-out with your Financial Outline (months 1 to 6, surplus before owner's pay)
A20: Model, with marketing added back as the outline does | E20: =SUM(J5:J10)+6*Assumptions!B14*Assumptions!B9 -> 148355.6
A21: Outline's stated total | E21: 148600
A22: Difference (the outline rounds to the nearest ₹100) | E22: =E20-E21 -> -244.39787

Sheet Break-even and Startup
A1: Startup Costs and Break-even
A2: Startup costs are from your Financial Outline (assumptions). Opening stock and cash reserve are not all spent upfront but count as capital needed.
A4: Startup item | B4: Amount (₹) | C4: Share
A5: Equipment | B5: 35000 | C5: =IF($B$10=0,0,B5/$B$10) -> 0.35
A6: Licensing and packaging | B6: 20000 | C6: =IF($B$10=0,0,B6/$B$10) -> 0.2
A7: Opening ingredient stock | B7: 15000 | C7: =IF($B$10=0,0,B7/$B$10) -> 0.15
A8: Marketing and photography | B8: 15000 | C8: =IF($B$10=0,0,B8/$B$10) -> 0.15
A9: Cash reserve | B9: 15000 | C9: =IF($B$10=0,0,B9/$B$10) -> 0.15
A10: Total startup cost | B10: =SUM(B5:B9) -> 100000 | C10: =SUM(C5:C9) -> 1
A12: Break-even by owner's pay scenario
A13: Scenario | B13: Owner's pay (₹/month) | C13: Fixed costs plus owner's pay (₹) | D13: Break-even orders per month | E13: Break-even orders per week | F13: Break-even monthly revenue (₹)
A14: No owner's pay | B14: 0 | C14: =Assumptions!$B$19+B14 -> 5800 | D14: =IF(Products!$B$20<=0,0,ROUNDUP(C14/Products!$B$20,0)) -> 17 | E14: =IF(Assumptions!$B$5=0,0,ROUNDUP(D14/Assumptions!$B$5,0)) -> 4 | F14: =D14*Products!$B$14 -> 11344.667
A15: Owner's pay ₹15,000 | B15: 15000 | C15: =Assumptions!$B$19+B15 -> 20800 | D15: =IF(Products!$B$20<=0,0,ROUNDUP(C15/Products!$B$20,0)) -> 58 | E15: =IF(Assumptions!$B$5=0,0,ROUNDUP(D15/Assumptions!$B$5,0)) -> 14 | F15: =D15*Products!$B$14 -> 38705.333
A16: Owner's pay ₹25,000 | B16: 25000 | C16: =Assumptions!$B$19+B16 -> 30800 | D16: =IF(Products!$B$20<=0,0,ROUNDUP(C16/Products!$B$20,0)) -> 86 | E16: =IF(Assumptions!$B$5=0,0,ROUNDUP(D16/Assumptions!$B$5,0)) -> 20 | F16: =D16*Products!$B$14 -> 57390.667
A18: Summary
A19: Measure | B19: Value
A20: Contribution per order (₹) | B20: =Products!B20 -> 359.11333
A21: Payback month for startup cost (after owner's pay) | B21: =IFERROR(INDEX('Monthly Projection'!A5:A16,MATCH(1,'Monthly Projection'!N5:N16,0)),"Not within 12 months") -> 8
A22: Steady-state monthly surplus before owner's pay (₹) | B22: =Products!I10*Assumptions!B5*Products!B20-Assumptions!B19 -> 40848.822
A23: Steady-state monthly surplus after owner's pay (₹) | B23: =B22-Assumptions!B20 -> 25848.822
A25: Sensitivity at steady state (monthly surplus)
A26: Orders per week | B26: Before owner's pay (₹) | C26: After owner's pay (₹)
A27: 20 | B27: =A27*Assumptions!$B$5*Products!$B$20-Assumptions!$B$19 -> 25299.215 | C27: =B27-Assumptions!$B$20 -> 10299.215
A28: 25 | B28: =A28*Assumptions!$B$5*Products!$B$20-Assumptions!$B$19 -> 33074.018 | C28: =B28-Assumptions!$B$20 -> 18074.018
A29: 30 | B29: =A29*Assumptions!$B$5*Products!$B$20-Assumptions!$B$19 -> 40848.822 | C29: =B29-Assumptions!$B$20 -> 25848.822
A31: Taxes (GST, income tax) are not modelled, as in the outline.
